untappd/__init__.py
untappd-0.5.dist-info/METADATA
untappd-0.5.dist-info/WHEEL
untappd-0.5.dist-info/licenses/LICENSE
untappd-0.5.dist-info/RECORD
