Metadata-Version: 2.1
Name: untappd
Version: 0.5
Summary: Untappd wrapper library
Project-URL: Homepage, https://github.com/cbetz/untappd-python
Project-URL: Bug Tracker, https://github.com/cbetz/untappd-python/issues
Author-email: Christopher Betz <christopherwilliambetz@gmail.com>
License-File: LICENSE
Classifier: Development Status :: 3 - Alpha
Classifier: Intended Audience :: Developers
Classifier: License :: OSI Approved :: MIT License
Classifier: Natural Language :: English
Classifier: Operating System :: OS Independent
Classifier: Programming Language :: Python
Classifier: Topic :: Internet :: WWW/HTTP :: Dynamic Content
Requires-Python: >=3.7
